Outliers_Python_101703101/Outliers_Python_101703101.py
Outliers_Python_101703101/__init__.py
Outliers_Python_101703101-0.2.dist-info/METADATA
Outliers_Python_101703101-0.2.dist-info/WHEEL
Outliers_Python_101703101-0.2.dist-info/top_level.txt
Outliers_Python_101703101-0.2.dist-info/RECORD
