Metadata-Version: 2.1
Name: Outliers-Python-101703101
Version: 0.2
Summary: Library to Delete Outliers using Z-Index
Home-page: https://github.com/ArpitSingla/Outliers_Python_101703101
Author: Arpit Singla
Author-email: arpitsingla1999@gmail.com
License: MIT
Download-URL: https://github.com/ArpitSingla/Outliers_Python_101703101.git
Keywords: Outliers_Python_101703101
Platform: UNKNOWN
Classifier: Development Status :: 5 - Production/Stable
Classifier: Intended Audience :: Developers
Classifier: Topic :: Software Development :: Build Tools
Classifier: License :: OSI Approved :: MIT License
Classifier: Programming Language :: Python :: 3
Classifier: Programming Language :: Python :: 3.4
Classifier: Programming Language :: Python :: 3.5
Classifier: Programming Language :: Python :: 3.6
Classifier: Programming Language :: Python :: 3.7
Requires-Dist: python
Requires-Dist: numpy
